[
    {
        "x": 100,
        "y": 15,
        "class": "Te"
    },
    {
        "x": 82,
        "y": 7,
        "class": "Te"
    },
    {
        "x": 98,
        "y": 117,
        "class": "Te"
    },
    {
        "x": 32,
        "y": 68,
        "class": "Te"
    },
    {
        "x": 53,
        "y": 78,
        "class": "Te"
    },
    {
        "x": 126,
        "y": 44,
        "class": "Te"
    },
    {
        "x": 4,
        "y": 101,
        "class": "Te"
    },
    {
        "x": 51,
        "y": 35,
        "class": "Te"
    },
    {
        "x": 76,
        "y": 65,
        "class": "Te"
    },
    {
        "x": 21,
        "y": 2,
        "class": "Te"
    },
    {
        "x": 27,
        "y": 89,
        "class": "Te"
    },
    {
        "x": 40,
        "y": 10,
        "class": "Te"
    },
    {
        "x": 99,
        "y": 56,
        "class": "Te"
    },
    {
        "x": 30,
        "y": 29,
        "class": "Te"
    },
    {
        "x": 63,
        "y": 102,
        "class": "Te"
    },
    {
        "x": 79,
        "y": 111,
        "class": "Te"
    },
    {
        "x": 10,
        "y": 83,
        "class": "Te"
    },
    {
        "x": 120,
        "y": 64,
        "class": "Te"
    },
    {
        "x": 107,
        "y": 38,
        "class": "Te"
    },
    {
        "x": 0,
        "y": 55,
        "class": "Te"
    },
    {
        "x": 118,
        "y": 126,
        "class": "Se"
    },
    {
        "x": 67,
        "y": 44,
        "class": "Se"
    },
    {
        "x": 83,
        "y": 49,
        "class": "Se"
    },
    {
        "x": 127,
        "y": 1,
        "class": "Se"
    },
    {
        "x": 117,
        "y": 21,
        "class": "Se"
    },
    {
        "x": 15,
        "y": 22,
        "class": "Se"
    },
    {
        "x": 88,
        "y": 31,
        "class": "Se"
    },
    {
        "x": 41,
        "y": 54,
        "class": "Se"
    },
    {
        "x": 23,
        "y": 109,
        "class": "Se"
    },
    {
        "x": 123,
        "y": 106,
        "class": "Se"
    },
    {
        "x": 109,
        "y": 99,
        "class": "Se"
    },
    {
        "x": 74,
        "y": 87,
        "class": "Se"
    },
    {
        "x": 47,
        "y": 100,
        "class": "Se"
    },
    {
        "x": 24,
        "y": 44,
        "class": "Se"
    },
    {
        "x": 62,
        "y": 63,
        "class": "Se"
    },
    {
        "x": 112,
        "y": 82,
        "class": "Se"
    },
    {
        "x": 10,
        "y": 39,
        "class": "Se"
    },
    {
        "x": 18,
        "y": 61,
        "class": "Se"
    },
    {
        "x": 41,
        "y": 116,
        "class": "Se"
    },
    {
        "x": 57,
        "y": 123,
        "class": "Se"
    },
    {
        "x": 91,
        "y": 93,
        "class": "Se"
    },
    {
        "x": 97,
        "y": 76,
        "class": "Se"
    },
    {
        "x": 57,
        "y": 16,
        "class": "Se"
    },
    {
        "x": 74,
        "y": 23,
        "class": "Se"
    }
]