[
    {
        "x": 98,
        "y": 101,
        "class": "Te"
    },
    {
        "x": 56,
        "y": 86,
        "class": "Te"
    },
    {
        "x": 112,
        "y": 88,
        "class": "Se"
    },
    {
        "x": 56,
        "y": 114,
        "class": "Te"
    },
    {
        "x": 69,
        "y": 74,
        "class": "Te"
    },
    {
        "x": 111,
        "y": 73,
        "class": "Te"
    },
    {
        "x": 98,
        "y": 86,
        "class": "Te"
    },
    {
        "x": 70,
        "y": 88,
        "class": "Te"
    },
    {
        "x": 98,
        "y": 74,
        "class": "Se"
    },
    {
        "x": 83,
        "y": 89,
        "class": "Se"
    },
    {
        "x": 42,
        "y": 75,
        "class": "Te"
    },
    {
        "x": 56,
        "y": 72,
        "class": "Se"
    },
    {
        "x": 71,
        "y": 115,
        "class": "Se"
    },
    {
        "x": 41,
        "y": 88,
        "class": "Te"
    },
    {
        "x": 83,
        "y": 46,
        "class": "Te"
    },
    {
        "x": 71,
        "y": 100,
        "class": "Te"
    },
    {
        "x": 55,
        "y": 58,
        "class": "Te"
    },
    {
        "x": 112,
        "y": 59,
        "class": "Te"
    },
    {
        "x": 26,
        "y": 48,
        "class": "Se"
    },
    {
        "x": 56,
        "y": 100,
        "class": "Te"
    },
    {
        "x": 11,
        "y": 4,
        "class": "Te"
    },
    {
        "x": 84,
        "y": 74,
        "class": "Se"
    },
    {
        "x": 12,
        "y": 73,
        "class": "Se"
    },
    {
        "x": 110,
        "y": 43,
        "class": "Te"
    },
    {
        "x": 69,
        "y": 59,
        "class": "Te"
    },
    {
        "x": 54,
        "y": 44,
        "class": "Te"
    },
    {
        "x": 98,
        "y": 58,
        "class": "Te"
    },
    {
        "x": 13,
        "y": 87,
        "class": "Te"
    },
    {
        "x": 84,
        "y": 101,
        "class": "Se"
    },
    {
        "x": 42,
        "y": 60,
        "class": "Se"
    },
    {
        "x": 111,
        "y": 16,
        "class": "Te"
    },
    {
        "x": 82,
        "y": 29,
        "class": "Te"
    },
    {
        "x": 12,
        "y": 18,
        "class": "Se"
    },
    {
        "x": 12,
        "y": 32,
        "class": "Te"
    },
    {
        "x": 42,
        "y": 30,
        "class": "Te"
    },
    {
        "x": 27,
        "y": 75,
        "class": "Se"
    },
    {
        "x": 112,
        "y": 30,
        "class": "Te"
    },
    {
        "x": 84,
        "y": 58,
        "class": "Te"
    },
    {
        "x": 29,
        "y": 116,
        "class": "Te"
    },
    {
        "x": 123,
        "y": 16,
        "class": "Te"
    },
    {
        "x": 27,
        "y": 88,
        "class": "Se"
    },
    {
        "x": 26,
        "y": 3,
        "class": "Te"
    },
    {
        "x": 95,
        "y": 46,
        "class": "Se"
    },
    {
        "x": 27,
        "y": 60,
        "class": "Te"
    },
    {
        "x": 12,
        "y": 59,
        "class": "Te"
    },
    {
        "x": 111,
        "y": 101,
        "class": "Se"
    },
    {
        "x": 26,
        "y": 17,
        "class": "Se"
    },
    {
        "x": 83,
        "y": 16,
        "class": "Te"
    },
    {
        "x": 26,
        "y": 31,
        "class": "Te"
    },
    {
        "x": 69,
        "y": 18,
        "class": "Te"
    },
    {
        "x": 39,
        "y": 17,
        "class": "Se"
    },
    {
        "x": 40,
        "y": 2,
        "class": "Te"
    },
    {
        "x": 42,
        "y": 101,
        "class": "Se"
    },
    {
        "x": 70,
        "y": 46,
        "class": "Te"
    },
    {
        "x": 88,
        "y": 114,
        "class": "Se"
    },
    {
        "x": 53,
        "y": 4,
        "class": "Te"
    },
    {
        "x": 55,
        "y": 30,
        "class": "Se"
    },
    {
        "x": 12,
        "y": 48,
        "class": "Se"
    },
    {
        "x": 96,
        "y": 3,
        "class": "Se"
    },
    {
        "x": 53,
        "y": 18,
        "class": "Se"
    },
    {
        "x": 27,
        "y": 101,
        "class": "Se"
    },
    {
        "x": 13,
        "y": 116,
        "class": "Se"
    },
    {
        "x": 123,
        "y": 111,
        "class": "Te"
    },
    {
        "x": 69,
        "y": 31,
        "class": "Se"
    },
    {
        "x": 12,
        "y": 103,
        "class": "Se"
    },
    {
        "x": 125,
        "y": 1,
        "class": "Se"
    },
    {
        "x": 40,
        "y": 46,
        "class": "Se"
    },
    {
        "x": 42,
        "y": 115,
        "class": "Se"
    },
    {
        "x": 111,
        "y": 127,
        "class": "Se"
    },
    {
        "x": 81,
        "y": 3,
        "class": "Se"
    },
    {
        "x": 68,
        "y": 4,
        "class": "Se"
    },
    {
        "x": 124,
        "y": 126,
        "class": "Te"
    },
    {
        "x": 122,
        "y": 100,
        "class": "Te"
    },
    {
        "x": 96,
        "y": 15,
        "class": "Se"
    },
    {
        "x": 111,
        "y": 0,
        "class": "Se"
    },
    {
        "x": 99,
        "y": 114,
        "class": "Se"
    },
    {
        "x": 96,
        "y": 30,
        "class": "Se"
    },
    {
        "x": 99,
        "y": 127,
        "class": "Se"
    },
    {
        "x": 123,
        "y": 44,
        "class": "Se"
    },
    {
        "x": 112,
        "y": 114,
        "class": "Se"
    },
    {
        "x": 123,
        "y": 33,
        "class": "Se"
    },
    {
        "x": 125,
        "y": 73,
        "class": "Se"
    },
    {
        "x": 125,
        "y": 58,
        "class": "Se"
    },
    {
        "x": 124,
        "y": 86,
        "class": "Te"
    }
]