[
    {
        "x": 77,
        "y": 28,
        "class": "Te"
    },
    {
        "x": 25,
        "y": 66,
        "class": "Te"
    },
    {
        "x": 12,
        "y": 19,
        "class": "Se"
    },
    {
        "x": 97,
        "y": 32,
        "class": "Se"
    },
    {
        "x": 65,
        "y": 37,
        "class": "Te"
    },
    {
        "x": 59,
        "y": 4,
        "class": "Te"
    },
    {
        "x": 112,
        "y": 24,
        "class": "Te"
    },
    {
        "x": 68,
        "y": 18,
        "class": "Te"
    },
    {
        "x": 12,
        "y": 73,
        "class": "Te"
    },
    {
        "x": 89,
        "y": 18,
        "class": "Te"
    },
    {
        "x": 125,
        "y": 68,
        "class": "Se"
    },
    {
        "x": 82,
        "y": 63,
        "class": "Se"
    },
    {
        "x": 20,
        "y": 30,
        "class": "Se"
    },
    {
        "x": 43,
        "y": 35,
        "class": "Se"
    },
    {
        "x": 89,
        "y": 75,
        "class": "Te"
    },
    {
        "x": 32,
        "y": 22,
        "class": "Te"
    },
    {
        "x": 95,
        "y": 53,
        "class": "Se"
    },
    {
        "x": 86,
        "y": 41,
        "class": "Se"
    },
    {
        "x": 52,
        "y": 46,
        "class": "Te"
    },
    {
        "x": 56,
        "y": 26,
        "class": "Se"
    },
    {
        "x": 101,
        "y": 11,
        "class": "Te"
    },
    {
        "x": 112,
        "y": 78,
        "class": "Se"
    },
    {
        "x": 119,
        "y": 35,
        "class": "Te"
    },
    {
        "x": 108,
        "y": 101,
        "class": "Te"
    },
    {
        "x": 26,
        "y": 122,
        "class": "Se"
    },
    {
        "x": 108,
        "y": 45,
        "class": "Te"
    },
    {
        "x": 68,
        "y": 73,
        "class": "Se"
    },
    {
        "x": 21,
        "y": 87,
        "class": "Se"
    },
    {
        "x": 29,
        "y": 43,
        "class": "Te"
    },
    {
        "x": 38,
        "y": 2,
        "class": "Se"
    },
    {
        "x": 48,
        "y": 68,
        "class": "Te"
    },
    {
        "x": 98,
        "y": 87,
        "class": "Te"
    },
    {
        "x": 103,
        "y": 67,
        "class": "Se"
    },
    {
        "x": 122,
        "y": 92,
        "class": "Te"
    },
    {
        "x": 39,
        "y": 56,
        "class": "Se"
    },
    {
        "x": 33,
        "y": 78,
        "class": "Te"
    },
    {
        "x": 15,
        "y": 53,
        "class": "Se"
    },
    {
        "x": 24,
        "y": 10,
        "class": "Se"
    },
    {
        "x": 30,
        "y": 98,
        "class": "Se"
    },
    {
        "x": 44,
        "y": 92,
        "class": "Se"
    },
    {
        "x": 4,
        "y": 62,
        "class": "Se"
    },
    {
        "x": 48,
        "y": 15,
        "class": "Se"
    },
    {
        "x": 63,
        "y": 118,
        "class": "Se"
    },
    {
        "x": 7,
        "y": 39,
        "class": "Te"
    },
    {
        "x": 62,
        "y": 60,
        "class": "Se"
    },
    {
        "x": 82,
        "y": 7,
        "class": "Se"
    },
    {
        "x": 87,
        "y": 97,
        "class": "Se"
    },
    {
        "x": 54,
        "y": 102,
        "class": "Te"
    },
    {
        "x": 77,
        "y": 85,
        "class": "Te"
    },
    {
        "x": 73,
        "y": 127,
        "class": "Se"
    },
    {
        "x": 117,
        "y": 58,
        "class": "Se"
    },
    {
        "x": 68,
        "y": 95,
        "class": "Se"
    },
    {
        "x": 9,
        "y": 96,
        "class": "Se"
    },
    {
        "x": 75,
        "y": 107,
        "class": "Se"
    },
    {
        "x": 18,
        "y": 107,
        "class": "Se"
    },
    {
        "x": 74,
        "y": 51,
        "class": "Se"
    },
    {
        "x": 49,
        "y": 124,
        "class": "Te"
    },
    {
        "x": 39,
        "y": 112,
        "class": "Te"
    },
    {
        "x": 97,
        "y": 111,
        "class": "Se"
    },
    {
        "x": 59,
        "y": 83,
        "class": "Se"
    },
    {
        "x": 86,
        "y": 119,
        "class": "Se"
    }
]