[
    {
        "x": 15,
        "y": 107,
        "class": "Se"
    },
    {
        "x": 119,
        "y": 15,
        "class": "Te"
    },
    {
        "x": 31,
        "y": 113,
        "class": "Te"
    },
    {
        "x": 117,
        "y": 64,
        "class": "Te"
    },
    {
        "x": 127,
        "y": 35,
        "class": "Te"
    },
    {
        "x": 41,
        "y": 49,
        "class": "Se"
    },
    {
        "x": 4,
        "y": 52,
        "class": "Se"
    },
    {
        "x": 37,
        "y": 97,
        "class": "Te"
    },
    {
        "x": 101,
        "y": 23,
        "class": "Se"
    },
    {
        "x": 113,
        "y": 28,
        "class": "Te"
    },
    {
        "x": 101,
        "y": 57,
        "class": "Te"
    },
    {
        "x": 41,
        "y": 83,
        "class": "Te"
    },
    {
        "x": 9,
        "y": 38,
        "class": "Se"
    },
    {
        "x": 104,
        "y": 8,
        "class": "Te"
    },
    {
        "x": 51,
        "y": 103,
        "class": "Te"
    },
    {
        "x": 61,
        "y": 74,
        "class": "Te"
    },
    {
        "x": 87,
        "y": 18,
        "class": "Te"
    },
    {
        "x": 20,
        "y": 59,
        "class": "Te"
    },
    {
        "x": 96,
        "y": 71,
        "class": "Se"
    },
    {
        "x": 120,
        "y": 48,
        "class": "Se"
    },
    {
        "x": 107,
        "y": 46,
        "class": "Te"
    },
    {
        "x": 42,
        "y": 1,
        "class": "Se"
    },
    {
        "x": 83,
        "y": 101,
        "class": "Se"
    },
    {
        "x": 69,
        "y": 61,
        "class": "Se"
    },
    {
        "x": 28,
        "y": 77,
        "class": "Te"
    },
    {
        "x": 15,
        "y": 24,
        "class": "Te"
    },
    {
        "x": 50,
        "y": 22,
        "class": "Se"
    },
    {
        "x": 6,
        "y": 86,
        "class": "Te"
    },
    {
        "x": 72,
        "y": 10,
        "class": "Se"
    },
    {
        "x": 23,
        "y": 92,
        "class": "Te"
    },
    {
        "x": 70,
        "y": 95,
        "class": "Te"
    },
    {
        "x": 78,
        "y": 115,
        "class": "Te"
    },
    {
        "x": 48,
        "y": 69,
        "class": "Te"
    },
    {
        "x": 53,
        "y": 55,
        "class": "Te"
    },
    {
        "x": 109,
        "y": 77,
        "class": "Te"
    },
    {
        "x": 79,
        "y": 31,
        "class": "Te"
    },
    {
        "x": 60,
        "y": 124,
        "class": "Se"
    },
    {
        "x": 94,
        "y": 37,
        "class": "Te"
    },
    {
        "x": 74,
        "y": 47,
        "class": "Te"
    },
    {
        "x": 63,
        "y": 111,
        "class": "Se"
    },
    {
        "x": 90,
        "y": 86,
        "class": "Te"
    },
    {
        "x": 56,
        "y": 90,
        "class": "Te"
    },
    {
        "x": 92,
        "y": 3,
        "class": "Se"
    },
    {
        "x": 12,
        "y": 71,
        "class": "Te"
    },
    {
        "x": 59,
        "y": 41,
        "class": "Te"
    },
    {
        "x": 33,
        "y": 62,
        "class": "Te"
    },
    {
        "x": 65,
        "y": 24,
        "class": "Te"
    },
    {
        "x": 25,
        "y": 41,
        "class": "Te"
    },
    {
        "x": 45,
        "y": 119,
        "class": "Se"
    },
    {
        "x": 59,
        "y": 7,
        "class": "Te"
    },
    {
        "x": 104,
        "y": 92,
        "class": "Te"
    },
    {
        "x": 82,
        "y": 67,
        "class": "Te"
    },
    {
        "x": 125,
        "y": 84,
        "class": "Se"
    },
    {
        "x": 75,
        "y": 82,
        "class": "Te"
    },
    {
        "x": 93,
        "y": 121,
        "class": "Se"
    },
    {
        "x": 88,
        "y": 52,
        "class": "Se"
    },
    {
        "x": 46,
        "y": 35,
        "class": "Se"
    },
    {
        "x": 36,
        "y": 16,
        "class": "Se"
    },
    {
        "x": 22,
        "y": 9,
        "class": "Se"
    },
    {
        "x": 120,
        "y": 99,
        "class": "Te"
    },
    {
        "x": 31,
        "y": 28,
        "class": "Se"
    },
    {
        "x": 114,
        "y": 113,
        "class": "Se"
    },
    {
        "x": 0,
        "y": 100,
        "class": "Se"
    },
    {
        "x": 98,
        "y": 108,
        "class": "Te"
    },
    {
        "x": 8,
        "y": 19,
        "class": "Se"
    },
    {
        "x": 2,
        "y": 32,
        "class": "Te"
    }
]