[
    {
        "x": 116,
        "y": 16,
        "class": "Se"
    },
    {
        "x": 69,
        "y": 73,
        "class": "Te"
    },
    {
        "x": 3,
        "y": 116,
        "class": "Te"
    },
    {
        "x": 74,
        "y": 108,
        "class": "Te"
    },
    {
        "x": 91,
        "y": 89,
        "class": "Te"
    },
    {
        "x": 71,
        "y": 93,
        "class": "Se"
    },
    {
        "x": 102,
        "y": 51,
        "class": "Te"
    },
    {
        "x": 14,
        "y": 44,
        "class": "Te"
    },
    {
        "x": 89,
        "y": 71,
        "class": "Se"
    },
    {
        "x": 107,
        "y": 85,
        "class": "Te"
    },
    {
        "x": 17,
        "y": 97,
        "class": "Se"
    },
    {
        "x": 86,
        "y": 54,
        "class": "Se"
    },
    {
        "x": 110,
        "y": 103,
        "class": "Te"
    },
    {
        "x": 121,
        "y": 67,
        "class": "Te"
    },
    {
        "x": 15,
        "y": 78,
        "class": "Te"
    },
    {
        "x": 33,
        "y": 75,
        "class": "Te"
    },
    {
        "x": 28,
        "y": 9,
        "class": "Te"
    },
    {
        "x": 94,
        "y": 126,
        "class": "Se"
    },
    {
        "x": 105,
        "y": 70,
        "class": "Se"
    },
    {
        "x": 100,
        "y": 18,
        "class": "Se"
    },
    {
        "x": 127,
        "y": 98,
        "class": "Te"
    },
    {
        "x": 36,
        "y": 95,
        "class": "Te"
    },
    {
        "x": 118,
        "y": 33,
        "class": "Se"
    },
    {
        "x": 65,
        "y": 39,
        "class": "Te"
    },
    {
        "x": 49,
        "y": 43,
        "class": "Te"
    },
    {
        "x": 37,
        "y": 112,
        "class": "Te"
    },
    {
        "x": 6,
        "y": 1,
        "class": "Se"
    },
    {
        "x": 49,
        "y": 58,
        "class": "Se"
    },
    {
        "x": 82,
        "y": 40,
        "class": "Se"
    },
    {
        "x": 52,
        "y": 94,
        "class": "Se"
    },
    {
        "x": 44,
        "y": 8,
        "class": "Te"
    },
    {
        "x": 110,
        "y": 121,
        "class": "Se"
    },
    {
        "x": 101,
        "y": 34,
        "class": "Se"
    },
    {
        "x": 76,
        "y": 125,
        "class": "Se"
    },
    {
        "x": 122,
        "y": 49,
        "class": "Se"
    },
    {
        "x": 62,
        "y": 3,
        "class": "Te"
    },
    {
        "x": 124,
        "y": 78,
        "class": "Te"
    },
    {
        "x": 63,
        "y": 21,
        "class": "Te"
    },
    {
        "x": 92,
        "y": 110,
        "class": "Se"
    },
    {
        "x": 53,
        "y": 75,
        "class": "Se"
    },
    {
        "x": 28,
        "y": 29,
        "class": "Se"
    },
    {
        "x": 31,
        "y": 43,
        "class": "Se"
    },
    {
        "x": 68,
        "y": 57,
        "class": "Se"
    },
    {
        "x": 12,
        "y": 29,
        "class": "Se"
    },
    {
        "x": 32,
        "y": 58,
        "class": "Se"
    },
    {
        "x": 1,
        "y": 100,
        "class": "Se"
    },
    {
        "x": 82,
        "y": 19,
        "class": "Te"
    },
    {
        "x": 20,
        "y": 114,
        "class": "Se"
    },
    {
        "x": 56,
        "y": 111,
        "class": "Se"
    },
    {
        "x": 60,
        "y": 126,
        "class": "Se"
    },
    {
        "x": 16,
        "y": 62,
        "class": "Se"
    },
    {
        "x": 45,
        "y": 24,
        "class": "Se"
    },
    {
        "x": 10,
        "y": 13,
        "class": "Se"
    }
]