[
    {
        "x": 10,
        "y": 70,
        "class": "Se"
    },
    {
        "x": 61,
        "y": 67,
        "class": "Te"
    },
    {
        "x": 95,
        "y": 57,
        "class": "Te"
    },
    {
        "x": 13,
        "y": 56,
        "class": "Se"
    },
    {
        "x": 58,
        "y": 84,
        "class": "Se"
    },
    {
        "x": 63,
        "y": 50,
        "class": "Te"
    },
    {
        "x": 43,
        "y": 81,
        "class": "Se"
    },
    {
        "x": 38,
        "y": 95,
        "class": "Te"
    },
    {
        "x": 27,
        "y": 77,
        "class": "Se"
    },
    {
        "x": 21,
        "y": 109,
        "class": "Se"
    },
    {
        "x": 37,
        "y": 110,
        "class": "Se"
    },
    {
        "x": 16,
        "y": 42,
        "class": "Te"
    },
    {
        "x": 34,
        "y": 44,
        "class": "Se"
    },
    {
        "x": 17,
        "y": 123,
        "class": "Te"
    },
    {
        "x": 79,
        "y": 54,
        "class": "Se"
    },
    {
        "x": 33,
        "y": 126,
        "class": "Se"
    },
    {
        "x": 7,
        "y": 88,
        "class": "Te"
    },
    {
        "x": 28,
        "y": 60,
        "class": "Te"
    },
    {
        "x": 117,
        "y": 114,
        "class": "Se"
    },
    {
        "x": 45,
        "y": 64,
        "class": "Te"
    },
    {
        "x": 66,
        "y": 102,
        "class": "Se"
    },
    {
        "x": 2,
        "y": 37,
        "class": "Se"
    },
    {
        "x": 100,
        "y": 42,
        "class": "Te"
    },
    {
        "x": 24,
        "y": 94,
        "class": "Se"
    },
    {
        "x": 54,
        "y": 98,
        "class": "Se"
    },
    {
        "x": 76,
        "y": 69,
        "class": "Te"
    },
    {
        "x": 120,
        "y": 96,
        "class": "Se"
    },
    {
        "x": 50,
        "y": 114,
        "class": "Se"
    },
    {
        "x": 126,
        "y": 64,
        "class": "Te"
    },
    {
        "x": 63,
        "y": 116,
        "class": "Se"
    },
    {
        "x": 87,
        "y": 23,
        "class": "Se"
    },
    {
        "x": 112,
        "y": 61,
        "class": "Se"
    },
    {
        "x": 107,
        "y": 10,
        "class": "Se"
    },
    {
        "x": 49,
        "y": 48,
        "class": "Se"
    },
    {
        "x": 123,
        "y": 80,
        "class": "Se"
    },
    {
        "x": 84,
        "y": 105,
        "class": "Te"
    },
    {
        "x": 91,
        "y": 9,
        "class": "Te"
    },
    {
        "x": 119,
        "y": 30,
        "class": "Se"
    },
    {
        "x": 72,
        "y": 85,
        "class": "Te"
    },
    {
        "x": 24,
        "y": 10,
        "class": "Se"
    },
    {
        "x": 87,
        "y": 39,
        "class": "Se"
    },
    {
        "x": 21,
        "y": 25,
        "class": "Se"
    },
    {
        "x": 76,
        "y": 5,
        "class": "Te"
    },
    {
        "x": 91,
        "y": 72,
        "class": "Se"
    },
    {
        "x": 99,
        "y": 127,
        "class": "Se"
    },
    {
        "x": 103,
        "y": 25,
        "class": "Te"
    },
    {
        "x": 69,
        "y": 35,
        "class": "Te"
    },
    {
        "x": 5,
        "y": 20,
        "class": "Se"
    },
    {
        "x": 0,
        "y": 120,
        "class": "Te"
    },
    {
        "x": 121,
        "y": 14,
        "class": "Te"
    },
    {
        "x": 73,
        "y": 21,
        "class": "Te"
    },
    {
        "x": 107,
        "y": 75,
        "class": "Te"
    },
    {
        "x": 3,
        "y": 106,
        "class": "Te"
    },
    {
        "x": 104,
        "y": 112,
        "class": "Te"
    },
    {
        "x": 115,
        "y": 46,
        "class": "Se"
    },
    {
        "x": 56,
        "y": 1,
        "class": "Te"
    },
    {
        "x": 53,
        "y": 32,
        "class": "Se"
    },
    {
        "x": 7,
        "y": 6,
        "class": "Te"
    },
    {
        "x": 40,
        "y": 12,
        "class": "Se"
    },
    {
        "x": 83,
        "y": 121,
        "class": "Te"
    },
    {
        "x": 88,
        "y": 87,
        "class": "Te"
    },
    {
        "x": 58,
        "y": 17,
        "class": "Te"
    },
    {
        "x": 108,
        "y": 94,
        "class": "Te"
    },
    {
        "x": 37,
        "y": 26,
        "class": "Se"
    }
]