[
    {
        "x": 115,
        "y": 14,
        "class": "Te"
    },
    {
        "x": 113,
        "y": 0,
        "class": "Se"
    },
    {
        "x": 37,
        "y": 6,
        "class": "Te"
    },
    {
        "x": 22,
        "y": 28,
        "class": "Se"
    },
    {
        "x": 120,
        "y": 123,
        "class": "Te"
    },
    {
        "x": 119,
        "y": 105,
        "class": "Te"
    },
    {
        "x": 4,
        "y": 57,
        "class": "Te"
    },
    {
        "x": 52,
        "y": 121,
        "class": "Te"
    },
    {
        "x": 48,
        "y": 67,
        "class": "Te"
    },
    {
        "x": 116,
        "y": 30,
        "class": "Te"
    },
    {
        "x": 55,
        "y": 106,
        "class": "Te"
    },
    {
        "x": 69,
        "y": 5,
        "class": "Se"
    },
    {
        "x": 20,
        "y": 40,
        "class": "Te"
    },
    {
        "x": 79,
        "y": 123,
        "class": "Se"
    },
    {
        "x": 24,
        "y": 3,
        "class": "Se"
    },
    {
        "x": 116,
        "y": 89,
        "class": "Te"
    },
    {
        "x": 30,
        "y": 67,
        "class": "Te"
    },
    {
        "x": 12,
        "y": 115,
        "class": "Te"
    },
    {
        "x": 105,
        "y": 15,
        "class": "Te"
    },
    {
        "x": 66,
        "y": 94,
        "class": "Se"
    },
    {
        "x": 109,
        "y": 122,
        "class": "Te"
    },
    {
        "x": 76,
        "y": 60,
        "class": "Se"
    },
    {
        "x": 66,
        "y": 106,
        "class": "Te"
    },
    {
        "x": 54,
        "y": 4,
        "class": "Te"
    },
    {
        "x": 12,
        "y": 104,
        "class": "Se"
    },
    {
        "x": 74,
        "y": 74,
        "class": "Te"
    },
    {
        "x": 38,
        "y": 48,
        "class": "Te"
    },
    {
        "x": 89,
        "y": 24,
        "class": "Te"
    },
    {
        "x": 67,
        "y": 121,
        "class": "Te"
    },
    {
        "x": 116,
        "y": 48,
        "class": "Te"
    },
    {
        "x": 7,
        "y": 30,
        "class": "Te"
    },
    {
        "x": 99,
        "y": 120,
        "class": "Te"
    },
    {
        "x": 30,
        "y": 101,
        "class": "Te"
    },
    {
        "x": 30,
        "y": 114,
        "class": "Te"
    },
    {
        "x": 13,
        "y": 89,
        "class": "Te"
    },
    {
        "x": 49,
        "y": 49,
        "class": "Te"
    },
    {
        "x": 38,
        "y": 26,
        "class": "Se"
    },
    {
        "x": 88,
        "y": 55,
        "class": "Te"
    },
    {
        "x": 81,
        "y": 99,
        "class": "Te"
    },
    {
        "x": 99,
        "y": 89,
        "class": "Te"
    },
    {
        "x": 80,
        "y": 5,
        "class": "Te"
    },
    {
        "x": 19,
        "y": 55,
        "class": "Se"
    },
    {
        "x": 56,
        "y": 18,
        "class": "Te"
    },
    {
        "x": 24,
        "y": 15,
        "class": "Se"
    },
    {
        "x": 72,
        "y": 20,
        "class": "Te"
    },
    {
        "x": 55,
        "y": 91,
        "class": "Te"
    },
    {
        "x": 63,
        "y": 39,
        "class": "Te"
    },
    {
        "x": 110,
        "y": 76,
        "class": "Se"
    },
    {
        "x": 38,
        "y": 38,
        "class": "Te"
    },
    {
        "x": 30,
        "y": 80,
        "class": "Te"
    },
    {
        "x": 74,
        "y": 32,
        "class": "Te"
    },
    {
        "x": 102,
        "y": 54,
        "class": "Se"
    },
    {
        "x": 61,
        "y": 50,
        "class": "Te"
    },
    {
        "x": 11,
        "y": 17,
        "class": "Te"
    },
    {
        "x": 20,
        "y": 66,
        "class": "Te"
    },
    {
        "x": 50,
        "y": 39,
        "class": "Se"
    },
    {
        "x": 47,
        "y": 82,
        "class": "Te"
    },
    {
        "x": 89,
        "y": 39,
        "class": "Te"
    },
    {
        "x": 118,
        "y": 68,
        "class": "Se"
    },
    {
        "x": 98,
        "y": 71,
        "class": "Te"
    },
    {
        "x": 62,
        "y": 62,
        "class": "Te"
    },
    {
        "x": 102,
        "y": 0,
        "class": "Se"
    },
    {
        "x": 6,
        "y": 41,
        "class": "Te"
    },
    {
        "x": 42,
        "y": 98,
        "class": "Te"
    },
    {
        "x": 107,
        "y": 99,
        "class": "Te"
    },
    {
        "x": 12,
        "y": 7,
        "class": "Te"
    },
    {
        "x": 127,
        "y": 13,
        "class": "Te"
    },
    {
        "x": 103,
        "y": 40,
        "class": "Se"
    },
    {
        "x": 93,
        "y": 104,
        "class": "Se"
    },
    {
        "x": 64,
        "y": 81,
        "class": "Te"
    },
    {
        "x": 81,
        "y": 88,
        "class": "Se"
    },
    {
        "x": 127,
        "y": 47,
        "class": "Te"
    }
]