[
    {
        "x": 110,
        "y": 105,
        "class": "Te"
    },
    {
        "x": 68,
        "y": 108,
        "class": "Se"
    },
    {
        "x": 83,
        "y": 122,
        "class": "Se"
    },
    {
        "x": 123,
        "y": 36,
        "class": "Te"
    },
    {
        "x": 52,
        "y": 8,
        "class": "Se"
    },
    {
        "x": 82,
        "y": 93,
        "class": "Se"
    },
    {
        "x": 11,
        "y": 121,
        "class": "Se"
    },
    {
        "x": 37,
        "y": 51,
        "class": "Te"
    },
    {
        "x": 123,
        "y": 120,
        "class": "Se"
    },
    {
        "x": 37,
        "y": 8,
        "class": "Te"
    },
    {
        "x": 80,
        "y": 36,
        "class": "Se"
    },
    {
        "x": 67,
        "y": 63,
        "class": "Se"
    },
    {
        "x": 126,
        "y": 79,
        "class": "Te"
    },
    {
        "x": 110,
        "y": 119,
        "class": "Te"
    },
    {
        "x": 110,
        "y": 78,
        "class": "Te"
    },
    {
        "x": 25,
        "y": 120,
        "class": "Te"
    },
    {
        "x": 8,
        "y": 79,
        "class": "Te"
    },
    {
        "x": 68,
        "y": 92,
        "class": "Te"
    },
    {
        "x": 54,
        "y": 93,
        "class": "Te"
    },
    {
        "x": 124,
        "y": 106,
        "class": "Te"
    },
    {
        "x": 81,
        "y": 50,
        "class": "Te"
    },
    {
        "x": 69,
        "y": 119,
        "class": "Te"
    },
    {
        "x": 52,
        "y": 36,
        "class": "Se"
    },
    {
        "x": 38,
        "y": 37,
        "class": "Se"
    },
    {
        "x": 96,
        "y": 92,
        "class": "Se"
    },
    {
        "x": 8,
        "y": 6,
        "class": "Te"
    },
    {
        "x": 81,
        "y": 65,
        "class": "Se"
    },
    {
        "x": 54,
        "y": 107,
        "class": "Te"
    },
    {
        "x": 110,
        "y": 91,
        "class": "Te"
    },
    {
        "x": 68,
        "y": 51,
        "class": "Se"
    },
    {
        "x": 95,
        "y": 78,
        "class": "Te"
    },
    {
        "x": 91,
        "y": 0,
        "class": "Te"
    },
    {
        "x": 82,
        "y": 107,
        "class": "Se"
    },
    {
        "x": 9,
        "y": 106,
        "class": "Te"
    },
    {
        "x": 123,
        "y": 92,
        "class": "Se"
    },
    {
        "x": 67,
        "y": 36,
        "class": "Se"
    },
    {
        "x": 23,
        "y": 66,
        "class": "Se"
    },
    {
        "x": 109,
        "y": 64,
        "class": "Se"
    },
    {
        "x": 95,
        "y": 37,
        "class": "Se"
    },
    {
        "x": 52,
        "y": 22,
        "class": "Se"
    },
    {
        "x": 66,
        "y": 22,
        "class": "Se"
    },
    {
        "x": 22,
        "y": 22,
        "class": "Te"
    },
    {
        "x": 67,
        "y": 77,
        "class": "Te"
    },
    {
        "x": 124,
        "y": 22,
        "class": "Te"
    },
    {
        "x": 9,
        "y": 93,
        "class": "Se"
    },
    {
        "x": 23,
        "y": 38,
        "class": "Se"
    },
    {
        "x": 39,
        "y": 107,
        "class": "Te"
    },
    {
        "x": 96,
        "y": 105,
        "class": "Te"
    },
    {
        "x": 52,
        "y": 50,
        "class": "Te"
    },
    {
        "x": 127,
        "y": 64,
        "class": "Te"
    },
    {
        "x": 81,
        "y": 79,
        "class": "Se"
    },
    {
        "x": 22,
        "y": 52,
        "class": "Se"
    },
    {
        "x": 108,
        "y": 36,
        "class": "Se"
    },
    {
        "x": 97,
        "y": 122,
        "class": "Se"
    },
    {
        "x": 39,
        "y": 120,
        "class": "Te"
    },
    {
        "x": 23,
        "y": 94,
        "class": "Te"
    },
    {
        "x": 8,
        "y": 22,
        "class": "Se"
    },
    {
        "x": 8,
        "y": 64,
        "class": "Te"
    },
    {
        "x": 95,
        "y": 64,
        "class": "Se"
    },
    {
        "x": 108,
        "y": 5,
        "class": "Te"
    },
    {
        "x": 96,
        "y": 50,
        "class": "Se"
    },
    {
        "x": 8,
        "y": 51,
        "class": "Se"
    },
    {
        "x": 38,
        "y": 78,
        "class": "Se"
    },
    {
        "x": 24,
        "y": 106,
        "class": "Se"
    },
    {
        "x": 53,
        "y": 119,
        "class": "Se"
    },
    {
        "x": 8,
        "y": 36,
        "class": "Te"
    },
    {
        "x": 38,
        "y": 91,
        "class": "Te"
    },
    {
        "x": 37,
        "y": 22,
        "class": "Te"
    },
    {
        "x": 37,
        "y": 66,
        "class": "Se"
    },
    {
        "x": 53,
        "y": 79,
        "class": "Te"
    },
    {
        "x": 51,
        "y": 65,
        "class": "Se"
    },
    {
        "x": 110,
        "y": 50,
        "class": "Te"
    },
    {
        "x": 23,
        "y": 80,
        "class": "Te"
    },
    {
        "x": 125,
        "y": 49,
        "class": "Te"
    },
    {
        "x": 23,
        "y": 7,
        "class": "Se"
    },
    {
        "x": 67,
        "y": 8,
        "class": "Se"
    },
    {
        "x": 78,
        "y": 21,
        "class": "Se"
    },
    {
        "x": 126,
        "y": 10,
        "class": "Se"
    },
    {
        "x": 90,
        "y": 17,
        "class": "Te"
    },
    {
        "x": 107,
        "y": 25,
        "class": "Te"
    },
    {
        "x": 78,
        "y": 6,
        "class": "Te"
    }
]