[
    {
        "x": 57,
        "y": 82,
        "class": "Te"
    },
    {
        "x": 98,
        "y": 38,
        "class": "Se"
    },
    {
        "x": 26,
        "y": 81,
        "class": "Te"
    },
    {
        "x": 27,
        "y": 53,
        "class": "Te"
    },
    {
        "x": 70,
        "y": 52,
        "class": "Te"
    },
    {
        "x": 26,
        "y": 40,
        "class": "Te"
    },
    {
        "x": 1,
        "y": 97,
        "class": "Te"
    },
    {
        "x": 23,
        "y": 8,
        "class": "Se"
    },
    {
        "x": 40,
        "y": 6,
        "class": "Se"
    },
    {
        "x": 57,
        "y": 94,
        "class": "Te"
    },
    {
        "x": 26,
        "y": 67,
        "class": "Te"
    },
    {
        "x": 70,
        "y": 24,
        "class": "Te"
    },
    {
        "x": 1,
        "y": 68,
        "class": "Te"
    },
    {
        "x": 57,
        "y": 67,
        "class": "Te"
    },
    {
        "x": 83,
        "y": 24,
        "class": "Te"
    },
    {
        "x": 85,
        "y": 40,
        "class": "Se"
    },
    {
        "x": 56,
        "y": 52,
        "class": "Te"
    },
    {
        "x": 43,
        "y": 124,
        "class": "Te"
    },
    {
        "x": 3,
        "y": 82,
        "class": "Te"
    },
    {
        "x": 115,
        "y": 81,
        "class": "Se"
    },
    {
        "x": 5,
        "y": 12,
        "class": "Se"
    },
    {
        "x": 69,
        "y": 8,
        "class": "Se"
    },
    {
        "x": 42,
        "y": 82,
        "class": "Te"
    },
    {
        "x": 54,
        "y": 7,
        "class": "Te"
    },
    {
        "x": 42,
        "y": 109,
        "class": "Te"
    },
    {
        "x": 86,
        "y": 121,
        "class": "Te"
    },
    {
        "x": 58,
        "y": 111,
        "class": "Se"
    },
    {
        "x": 84,
        "y": 81,
        "class": "Se"
    },
    {
        "x": 84,
        "y": 53,
        "class": "Se"
    },
    {
        "x": 42,
        "y": 95,
        "class": "Se"
    },
    {
        "x": 71,
        "y": 66,
        "class": "Te"
    },
    {
        "x": 115,
        "y": 107,
        "class": "Te"
    },
    {
        "x": 71,
        "y": 122,
        "class": "Se"
    },
    {
        "x": 41,
        "y": 25,
        "class": "Te"
    },
    {
        "x": 101,
        "y": 121,
        "class": "Te"
    },
    {
        "x": 72,
        "y": 82,
        "class": "Se"
    },
    {
        "x": 2,
        "y": 110,
        "class": "Te"
    },
    {
        "x": 85,
        "y": 94,
        "class": "Te"
    },
    {
        "x": 42,
        "y": 54,
        "class": "Te"
    },
    {
        "x": 99,
        "y": 24,
        "class": "Te"
    },
    {
        "x": 14,
        "y": 69,
        "class": "Se"
    },
    {
        "x": 98,
        "y": 9,
        "class": "Te"
    },
    {
        "x": 114,
        "y": 38,
        "class": "Se"
    },
    {
        "x": 27,
        "y": 109,
        "class": "Se"
    },
    {
        "x": 29,
        "y": 123,
        "class": "Te"
    },
    {
        "x": 41,
        "y": 69,
        "class": "Se"
    },
    {
        "x": 99,
        "y": 52,
        "class": "Te"
    },
    {
        "x": 112,
        "y": 9,
        "class": "Se"
    },
    {
        "x": 124,
        "y": 8,
        "class": "Te"
    },
    {
        "x": 72,
        "y": 109,
        "class": "Se"
    },
    {
        "x": 58,
        "y": 124,
        "class": "Te"
    },
    {
        "x": 82,
        "y": 8,
        "class": "Te"
    },
    {
        "x": 13,
        "y": 54,
        "class": "Te"
    },
    {
        "x": 56,
        "y": 41,
        "class": "Se"
    },
    {
        "x": 0,
        "y": 54,
        "class": "Te"
    },
    {
        "x": 14,
        "y": 81,
        "class": "Te"
    },
    {
        "x": 41,
        "y": 40,
        "class": "Te"
    },
    {
        "x": 71,
        "y": 94,
        "class": "Te"
    },
    {
        "x": 99,
        "y": 67,
        "class": "Te"
    },
    {
        "x": 85,
        "y": 109,
        "class": "Te"
    },
    {
        "x": 112,
        "y": 23,
        "class": "Se"
    },
    {
        "x": 0,
        "y": 38,
        "class": "Se"
    },
    {
        "x": 116,
        "y": 120,
        "class": "Te"
    },
    {
        "x": 12,
        "y": 39,
        "class": "Se"
    },
    {
        "x": 114,
        "y": 93,
        "class": "Se"
    },
    {
        "x": 4,
        "y": 24,
        "class": "Se"
    },
    {
        "x": 101,
        "y": 108,
        "class": "Se"
    },
    {
        "x": 100,
        "y": 95,
        "class": "Te"
    },
    {
        "x": 115,
        "y": 53,
        "class": "Se"
    },
    {
        "x": 25,
        "y": 25,
        "class": "Te"
    },
    {
        "x": 28,
        "y": 95,
        "class": "Te"
    },
    {
        "x": 55,
        "y": 24,
        "class": "Te"
    },
    {
        "x": 114,
        "y": 65,
        "class": "Te"
    },
    {
        "x": 99,
        "y": 80,
        "class": "Te"
    },
    {
        "x": 70,
        "y": 38,
        "class": "Te"
    },
    {
        "x": 15,
        "y": 98,
        "class": "Se"
    },
    {
        "x": 15,
        "y": 110,
        "class": "Se"
    },
    {
        "x": 85,
        "y": 66,
        "class": "Te"
    },
    {
        "x": 125,
        "y": 94,
        "class": "Te"
    },
    {
        "x": 14,
        "y": 122,
        "class": "Te"
    },
    {
        "x": 123,
        "y": 23,
        "class": "Te"
    },
    {
        "x": 127,
        "y": 67,
        "class": "Se"
    }
]